[
  {
    "Algorithm": "MPI-IMM",
    "DiffusionModel": "IC",
    "Epsilon": 0.13,
    "FindMostInfluentialSet": 2115.430714,
    "GenerateRRRSets": 620.266685,
    "Input": "BerkStan",
    "K": 100,
    "L": 1,
    "NumGPUWalkWorkers": 21,
    "NumThreads": 42,
    "NumWalkWorkers": 42,
    "Output": "BerkStan",
    "Rank": 0,
    "Seeds": [
      316707,
      61841,
      581996,
      25147,
      262976,
      519018,
      394748,
      500663,
      327967,
      630963,
      476912,
      562414,
      410390,
      423977,
      258427,
      526128,
      201056,
      587582,
      572493,
      163224,
      66172,
      635013,
      666764,
      604687,
      343490,
      588838,
      608289,
      271584,
      260800,
      369006,
      180627,
      223795,
      331981,
      252728,
      383159,
      536731,
      427843,
      227183,
      269953,
      394760,
      126648,
      506025,
      208015,
      280424,
      143837,
      607454,
      168961,
      335265,
      487185,
      515279,
      426356,
      331919,
      53603,
      537117,
      579168,
      494553,
      659378,
      389703,
      389731,
      207515,
      236875,
      353508,
      292256,
      260927,
      171587,
      584351,
      387237,
      60246,
      113039,
      536285,
      116080,
      111447,
      128502,
      114882,
      168367,
      394766,
      112477,
      272975,
      484432,
      389659,
      177447,
      407098,
      111035,
      115664,
      400826,
      588096,
      113730,
      110186,
      512962,
      571828,
      400277,
      417501,
      114265,
      281936,
      294211,
      389724,
      119424,
      583600,
      60279,
      189711
    ],
    "Theta": 269243,
    "ThetaEstimation": 8020.860599,
    "ThetaEstimationGenerateRRR": [
      1952.97702,
      1845.698628
    ],
    "ThetaEstimationMostInfluential": [
      1912.101635,
      2310.049092
    ],
    "ThetaPrimeDeltas": [
      7853,
      7852
    ],
    "Total": 10794.843805,
    "WorldSize": 16
  }
]
