[
  {
    "Algorithm": "MPI-IMM",
    "DiffusionModel": "IC",
    "Epsilon": 0.13,
    "FindMostInfluentialSet": 11241.635879,
    "GenerateRRRSets": 9.6e-05,
    "Input": "Orkut",
    "K": 100,
    "L": 1,
    "NumGPUWalkWorkers": 21,
    "NumThreads": 42,
    "NumWalkWorkers": 42,
    "Output": "Orkut",
    "Rank": 0,
    "Seeds": [
      6,
      692,
      97,
      28,
      1,
      1464,
      718,
      2,
      100,
      691,
      135,
      229,
      42370,
      14,
      55,
      83,
      125,
      259,
      2767,
      11072,
      46,
      77,
      120,
      648,
      1235,
      2586,
      6638,
      10928,
      11011,
      11100,
      34808,
      42225,
      42228,
      42274,
      42292,
      42567,
      43120,
      57588,
      63487,
      4,
      20,
      122,
      689,
      1112,
      1244,
      1438,
      1532,
      2570,
      2594,
      3495,
      3991,
      4291,
      6059,
      6842,
      7450,
      8593,
      9612,
      10208,
      10272,
      10915,
      11076,
      11104,
      11135,
      13196,
      33817,
      34789,
      42134,
      42166,
      42219,
      42315,
      42332,
      42366,
      42414,
      42481,
      42534,
      44958,
      47770,
      56796,
      57334,
      57560,
      57589,
      75882,
      79093,
      83686,
      86999,
      95107,
      106938,
      111296,
      148223,
      173011,
      206303,
      309632,
      347999,
      393435,
      413630,
      492319,
      511857,
      512226,
      582484,
      583702
    ],
    "Theta": 125863,
    "ThetaEstimation": 43084.945972,
    "ThetaEstimationGenerateRRR": [
      27925.250801
    ],
    "ThetaEstimationMostInfluential": [
      15159.673816
    ],
    "ThetaPrimeDeltas": [
      18086
    ],
    "Total": 54707.745742,
    "WorldSize": 8
  }
]
